fvalues/__init__.py
fvalues/f.py
fvalues/py.typed
fvalues/version.py
fvalues-0.0.4.dist-info/LICENSE.md
fvalues-0.0.4.dist-info/METADATA
fvalues-0.0.4.dist-info/WHEEL
fvalues-0.0.4.dist-info/top_level.txt
fvalues-0.0.4.dist-info/RECORD
