Metadata-Version: 2.1
Name: fvalues
Version: 0.0.4
Summary: Keep track of components in strings, especially formatted values in f-strings.
Home-page: https://github.com/oughtinc/fvalues
Author: Alex Hall
Author-email: alex.mojaki@gmail.com
License: MIT
Classifier: Programming Language :: Python :: 3.9
Classifier: Programming Language :: Python :: 3.10
Classifier: Programming Language :: Python :: 3.11
Classifier: License :: OSI Approved :: MIT License
Requires-Python: >=3.9
License-File: LICENSE.md
Requires-Dist: executing
Provides-Extra: dev
Requires-Dist: autoflake ; extra == 'dev'
Requires-Dist: black ; extra == 'dev'
Requires-Dist: flake8 ; extra == 'dev'
Requires-Dist: mypy ; extra == 'dev'
Requires-Dist: pre-commit ; extra == 'dev'
Requires-Dist: pylint ; extra == 'dev'
Requires-Dist: pytest ; extra == 'dev'
Requires-Dist: tox ; extra == 'dev'
